{"is_source_file": true, "format": "Python", "description": "A simple Python script that imports an application object 'app' from a module named 'app' and runs it if the script is executed as the main program.", "external_files": ["app"], "external_methods": ["app.run"], "published": [], "classes": [], "methods": [], "calls": ["app.run"], "search-terms": ["run.py", "main", "app"], "state": 2, "file_id": 5, "knowledge_revision": 10, "git_revision": "7c3ffc563a035922c7698fea2f7867c80ee4ea37", "ctags": [], "hash": "b4cfd2f2017c7f88e4049fa0ed026e86", "format-version": 4, "code-base-name": "recruitment_dashboard_gui", "filename": "recruitment_dashboard_gui/run.py", "revision_history": [{"10": "7c3ffc563a035922c7698fea2f7867c80ee4ea37"}]}